mongo_connector/__init__.py
mongo_connector/doc_managers/__init__.py
mongo_connector/doc_managers/solr_doc_manager.py
solr_doc_manager-0.1.0.dist-info/DESCRIPTION.rst
solr_doc_manager-0.1.0.dist-info/METADATA
solr_doc_manager-0.1.0.dist-info/RECORD
solr_doc_manager-0.1.0.dist-info/WHEEL
solr_doc_manager-0.1.0.dist-info/metadata.json
solr_doc_manager-0.1.0.dist-info/top_level.txt
